Workbook

Sheet receitas
A1: idreceita | B1: data_transacao | C1: nomecliente | D1: nomeproduto | E1: quantidade | F1: preco_unitario | G1: valor_total_receita | H1: mes_ano
A2: 1 | B2: 46237 | C2: Isaque Albuquerque | D2: Vacina contra Bipolaridade - Dose Única | E2: 2 | F2: 12658 | G2: =TbReceitas[[#This Row],[quantidade]]*TbReceitas[[#This Row],[preco_unitario]] -> 25316 | H2: =TEXT(TbReceitas[[#This Row],[data_transacao]], "aaaa-mm") -> 2026-08
A3: 2 | B3: 45822 | C3: Enrico Freitas | D3: Sertralina 1g - 10 Comprimidos - Bayer | E3: 2 | F3: 12969 | G3: =TbReceitas[[#This Row],[quantidade]]*TbReceitas[[#This Row],[preco_unitario]] -> 25938 | H3: =TEXT(TbReceitas[[#This Row],[data_transacao]], "aaaa-mm") -> 2025-06
A4: 3 | B4: 45700 | C4: Dra. Alana Moreira | D4: Vacina contra Lúpus - Dose Única | E4: 5 | F4: 11041 | G4: =TbReceitas[[#This Row],[quantidade]]*TbReceitas[[#This Row],[preco_unitario]] -> 55205 | H4: =TEXT(TbReceitas[[#This Row],[data_transacao]], "aaaa-mm") -> 2025-02
A5: 4 | B5: 45928 | C5: Thiago Rezende | D5: Tadalafila Gotas 20ml - EMS (Genérico) | E5: 2 | F5: 10155 | G5: =TbReceitas[[#This Row],[quantidade]]*TbReceitas[[#This Row],[preco_unitario]] -> 20310 | H5: =TEXT(TbReceitas[[#This Row],[data_transacao]], "aaaa-mm") -> 2025-09
A6: 5 | B6: 45827 | C6: Brenda da Paz | D6: Escitalopram Xarope 120ml - EMS (Genérico) | E6: 1 | F6: 23302 | G6: =TbReceitas[[#This Row],[quantidade]]*TbReceitas[[#This Row],[preco_unitario]] -> 23302 | H6: =TEXT(TbReceitas[[#This Row],[data_transacao]], "aaaa-mm") -> 2025-06
A7: 6 | B7: 45717 | C7: Sr. Otávio Nunes | D7: Sabonete em Barra Pampers 90g | E7: 2 | F7: 2647 | G7: =TbReceitas[[#This Row],[quantidade]]*TbReceitas[[#This Row],[preco_unitario]] -> 5294 | H7: =TEXT(TbReceitas[[#This Row],[data_transacao]], "aaaa-mm") -> 2025-03
A8: 7 | B8: 45827 | C8: Luiz Felipe Farias | D8: Vacina contra Otite - Dose Única | E8: 2 | F8: 13503 | G8: =TbReceitas[[#This Row],[quantidade]]*TbReceitas[[#This Row],[preco_unitario]] -> 27006 | H8: =TEXT(TbReceitas[[#This Row],[data_transacao]], "aaaa-mm") -> 2025-06
A9: 8 | B9: 45651 | C9: Dr. João Lucas Cavalcante | D9: Hidroclorotiazida Xarope 120ml - Medley (Genérico) | E9: 4 | F9: 9276 | G9: =TbReceitas[[#This Row],[quantidade]]*TbReceitas[[#This Row],[preco_unitario]] -> 37104 | H9: =TEXT(TbReceitas[[#This Row],[data_transacao]], "aaaa-mm") -> 2024-12
A10: 9 | B10: 45899 | C10: Yasmin Pinto | D10: Absorvente com Abas Johnson's 150ml | E10: 1 | F10: 24879 | G10: =TbReceitas[[#This Row],[quantidade]]*TbReceitas[[#This Row],[preco_unitario]] -> 24879 | H10: =TEXT(TbReceitas[[#This Row],[data_transacao]], "aaaa-mm") -> 2025-08
A11: 10 | B11: 46134 | C11: Ana Vitória Abreu | D11: Creme Hidratante CeraVe 500ml | E11: 3 | F11: 5365 | G11: =TbReceitas[[#This Row],[quantidade]]*TbReceitas[[#This Row],[preco_unitario]] -> 16095 | H11: =TEXT(TbReceitas[[#This Row],[data_transacao]], "aaaa-mm") -> 2026-04
A12: 11 | B12: 46152 | C12: Sr. Henry Gomes | D12: Atenolol 1g - 10 Comprimidos - Aché | E12: 1 | F12: 13019 | G12: =TbReceitas[[#This Row],[quantidade]]*TbReceitas[[#This Row],[preco_unitario]] -> 13019 | H12: =TEXT(TbReceitas[[#This Row],[data_transacao]], "aaaa-mm") -> 2026-05
A13: 12 | B13: 46107 | C13: Yan Correia | D13: Soro Fisiológico CeraVe FPS 50 | E13: 5 | F13: 13342 | G13: =TbReceitas[[#This Row],[quantidade]]*TbReceitas[[#This Row],[preco_unitario]] -> 66710 | H13: =TEXT(TbReceitas[[#This Row],[data_transacao]], "aaaa-mm") -> 2026-03
... A3001: 3000 | B3001: 45738 | C3001: Dr. Caio Fernandes | D3001: Soro Fisiológico Sempre Livre 50 Metros | E3001: 3 | F3001: 3035 | G3001: =TbReceitas[[#This Row],[quantidade]]*TbReceitas[[#This Row],[preco_unitario]] -> 9105 | H3001: =TEXT(TbReceitas[[#This Row],[data_transacao]], "aaaa-mm") -> 2025-03

Sheet despesas
A1: iddespesa | B1: data_transacao | C1: nomefornecedor | D1: nomeproduto | E1: quantidade | F1: preco_unitario | G1: valor_total_despesa | H1: mes_ano
A2: 1 | B2: 45919 | C2: Freitas Cassiano e Filhos | D2: Pomada para Assaduras Rexona 90g | E2: 19 | F2: 148 | G2: 2827 | H2: =TEXT(TbDespesas[[#This Row],[data_transacao]], "aaaa-mm") -> 2025-09
A3: 2 | B3: 45919 | C3: Freitas Cassiano e Filhos | D3: Omeprazol Pomada 30g - EMS (Genérico) | E3: 164 | F3: 14 | G3: 2334 | H3: =TEXT(TbDespesas[[#This Row],[data_transacao]], "aaaa-mm") -> 2025-09
A4: 3 | B4: 45919 | C4: Freitas Cassiano e Filhos | D4: Escitalopram 25mg - 30 Comprimidos - Aché | E4: 263 | F4: 8 | G4: 2260 | H4: =TEXT(TbDespesas[[#This Row],[data_transacao]], "aaaa-mm") -> 2025-09
A5: 4 | B5: 45919 | C5: Freitas Cassiano e Filhos | D5: Vacina contra Anemia - Dose Única | E5: 167 | F5: 5 | G5: 969 | H5: =TEXT(TbDespesas[[#This Row],[data_transacao]], "aaaa-mm") -> 2025-09
A6: 5 | B6: 45919 | C6: Freitas Cassiano e Filhos | D6: Fluoxetina 25mg - 30 Comprimidos - Aché | E6: 435 | F6: 5 | G6: 2333 | H6: =TEXT(TbDespesas[[#This Row],[data_transacao]], "aaaa-mm") -> 2025-09
A7: 6 | B7: 46013 | C7: Monteiro - ME | D7: Vacina contra Hipertensão - Reforço | E7: 111 | F7: 22 | G7: 2512 | H7: =TEXT(TbDespesas[[#This Row],[data_transacao]], "aaaa-mm") -> 2025-12
A8: 7 | B8: 46013 | C8: Monteiro - ME | D8: Losartana Potássica 500mg - 20 Comprimidos - Aché | E8: 226 | F8: 7 | G8: 1710 | H8: =TEXT(TbDespesas[[#This Row],[data_transacao]], "aaaa-mm") -> 2025-12
A9: 8 | B9: 46013 | C9: Monteiro - ME | D9: Creme Dental Nivea Tamanho G (32 un) | E9: 493 | F9: 4 | G9: 2055 | H9: =TEXT(TbDespesas[[#This Row],[data_transacao]], "aaaa-mm") -> 2025-12
A10: 9 | B10: 46013 | C10: Monteiro - ME | D10: Vacina contra Hipertireoidismo - Reforço | E10: 396 | F10: 0 | G10: 54 | H10: =TEXT(TbDespesas[[#This Row],[data_transacao]], "aaaa-mm") -> 2025-12
A11: 10 | B11: 46013 | C11: Monteiro - ME | D11: Sertralina Suspensão Oral 50ml - Eurofarma | E11: 397 | F11: 5 | G11: 2340 | H11: =TEXT(TbDespesas[[#This Row],[data_transacao]], "aaaa-mm") -> 2025-12
A12: 11 | B12: 46013 | C12: Monteiro - ME | D12: Soro Fisiológico CeraVe FPS 50 | E12: 451 | F12: 3 | G12: 1570 | H12: =TEXT(TbDespesas[[#This Row],[data_transacao]], "aaaa-mm") -> 2025-12
A13: 12 | B13: 46013 | C13: Monteiro - ME | D13: Escitalopram 25mg - 30 Comprimidos - Medley (Genérico) | E13: 455 | F13: 1 | G13: 780 | H13: =TEXT(TbDespesas[[#This Row],[data_transacao]], "aaaa-mm") -> 2025-12
... A1936: 1935 | B1936: 46224 | C1936: Castro da Rosa - EI | D1936: Sérum Vitamina C Nivea 200ml | E1936: 352 | F1936: 6 | G1936: 2357 | H1936: =TEXT(TbDespesas[[#This Row],[data_transacao]], "aaaa-mm") -> 2026-07

Sheet ReceitaDespesa
A1: MESES | B1: RECEITAS | C1: DESPESAS | D1: LUCRO | E1: VOL/TicMedio
A2: {=_xlfn.UNIQUE(_xlfn._xlws.SORT(_xlfn.VSTACK(TbReceitas[mes_ano], TbDespesas[mes_ano])))} -> 2024-09 | B2: {=SUMIFS(TbReceitas[valor_total_receita], TbReceitas[mes_ano],_xlfn.ANCHORARRAY( A2))} -> 2906675 | C2: {=SUMIFS(TbDespesas[valor_total_despesa], TbDespesas[mes_ano],_xlfn.ANCHORARRAY( A2))} -> 0 | D2: {=_xlfn.ANCHORARRAY(B2) -_xlfn.ANCHORARRAY( C2)} -> 2906675 | E2: {=IF(DashBoard!$R$22="Volume", SUMIFS(TbReceitas[quantidade], TbReceitas[mes_ano],_xlfn.ANCHORARRAY( A2)), SUMIFS(TbReceitas[valor_total_receita], TbReceitas[mes_ano],_xlfn.ANCHORARRAY( A2)) / COUNTIF(TbReceitas[mes_ano],_xlfn.ANCHORARRAY( A2)))} -> 245
A3: 2024-10 | B3: 4576658 | C3: 0 | D3: 4576658 | E3: 423
A4: 2024-11 | B4: 4290587 | C4: 0 | D4: 4290587 | E4: 393
A5: 2024-12 | B5: 5430932 | C5: 0 | D5: 5430932 | E5: 454
A6: 2025-01 | B6: 4154325 | C6: 0 | D6: 4154325 | E6: 381
A7: 2025-02 | B7: 3652181 | C7: 0 | D7: 3652181 | E7: 314
A8: 2025-03 | B8: 4037482 | C8: 0 | D8: 4037482 | E8: 352
A9: 2025-04 | B9: 3257222 | C9: 0 | D9: 3257222 | E9: 321
A10: 2025-05 | B10: 4215011 | C10: 0 | D10: 4215011 | E10: 366
A11: 2025-06 | B11: 3800465 | C11: 0 | D11: 3800465 | E11: 337
A12: 2025-07 | B12: 3721447 | C12: 0 | D12: 3721447 | E12: 305
A13: 2025-08 | B13: 4459814 | C13: 0 | D13: 4459814 | E13: 386
A14: 2025-09 | B14: 5251479 | C14: 155787 | D14: 5095692 | E14: 429
... A26: 2026-09 | B26: 2103639 | C26: 140846 | D26: 1962793 | E26: 180

Sheet TopLucros
A1: PRODUTO | B1: VENDA TOTAL | C1: LUCRO
A2: {=_xlfn.UNIQUE(_xlfn.VSTACK(TbReceitas[nomeproduto], TbDespesas[nomeproduto]))} -> Vacina contra Bipolaridade - Dose Única | B2: {=SUMIFS(TbReceitas[valor_total_receita], TbReceitas[nomeproduto],_xlfn.ANCHORARRAY( A2))} -> 189870 | C2: {=_xlfn.ANCHORARRAY(B2) - SUMIFS(TbDespesas[valor_total_despesa], TbDespesas[nomeproduto],_xlfn.ANCHORARRAY( A2))} -> 185117 | F2: {=_xlfn.TAKE(_xlfn._xlws.SORT(_xlfn.HSTACK(_xlfn.ANCHORARRAY(A2),_xlfn.ANCHORARRAY( B2),_xlfn.ANCHORARRAY( C2)), 2, -1), DashBoard!$A$7)} -> Absorvente com Abas Johnson's 150ml | G2: 970281 | H2: 960832
A3: Sertralina 1g - 10 Comprimidos - Bayer | B3: 168597 | C3: 166190 | F3: Amoxicilina 25mg - 30 Comprimidos - Eurofarma | G3: 741458 | H3: 728848
A4: Vacina contra Lúpus - Dose Única | B4: 165615 | C4: 147522 | F4: Escitalopram Suspensão Oral 50ml - Eurofarma | G4: 665896 | H4: 655531
A5: Tadalafila Gotas 20ml - EMS (Genérico) | B5: 172635 | C5: 167401 | F5: Paracetamol 500mg - 20 Comprimidos - Medley (Genérico) | G5: 647187 | H5: 644044
A6: Escitalopram Xarope 120ml - EMS (Genérico) | B6: 372832 | C6: 364651 | F6: Paracetamol Xarope 120ml - EMS (Genérico) | G6: 613904 | H6: 610157
A7: Sabonete em Barra Pampers 90g | B7: 68822 | C7: 51266 | F7: Ibuprofeno 50mg - 30 Comprimidos - Medley (Genérico) | G7: 608675 | H7: 605904
A8: Vacina contra Otite - Dose Única | B8: 54012 | C8: 52943 | F8: Creme Dental Nivea Tamanho G (32 un) | G8: 577071 | H8: 566230
A9: Hidroclorotiazida Xarope 120ml - Medley (Genérico) | B9: 139140 | C9: 137115 | F9: Azitromicina Pomada 30g - Medley (Genérico) | G9: 572049 | H9: 559412
A10: Absorvente com Abas Johnson's 150ml | B10: 970281 | C10: 960832
A11: Creme Hidratante CeraVe 500ml | B11: 80475 | C11: 63055
A12: Atenolol 1g - 10 Comprimidos - Aché | B12: 208304 | C12: 196562
A13: Soro Fisiológico CeraVe FPS 50 | B13: 80052 | C13: 73840
A14: Atenolol 1g - 10 Comprimidos - Medley (Genérico) | B14: 349995 | C14: 340194 | F14: Validação de dados | H14: Título do Gráfico
A15: Desodorante Roll-on Aptamil 50g | B15: 26850 | C15: 20108 | F15: 1 | H15: ="Lucro dos Top " & DashBoard!A7 & " Produtos" -> Lucro dos Top 8 Produtos
A16: Sabonete em Barra Nivea Tamanho M (40 un) | B16: 28709 | C16: 28709 | F16: 2
A17: Azitromicina 1g - 10 Comprimidos - EMS (Genérico) | B17: 216564 | C17: 210460 | F17: 3
A18: Loratadina Gotas 20ml - Medley (Genérico) | B18: 224128 | C18: 219959 | F18: 4
A19: Amoxicilina 50mg - 30 Comprimidos - EMS (Genérico) | B19: 419727 | C19: 405882 | F19: 5
A20: Cefalexina 500mg - 20 Comprimidos - Medley (Genérico) | B20: 223150 | C20: 215756 | F20: 6
A21: Absorvente com Abas Nivea 200ml | B21: 444300 | C21: 442493 | F21: 7
A22: Ibuprofeno 50mg - 30 Comprimidos - Medley (Genérico) | B22: 608675 | C22: 605904 | F22: 8
A23: Enxaguante Bucal Pampers 500ml | B23: 483900 | C23: 480434 | F23: 9
A24: Shampoo Anticaspa Mió 90g | B24: 98923 | C24: 92212 | F24: 10
A25: Sildenafila 50mg - 30 Comprimidos - Medley (Genérico) | B25: 80104 | C25: 70299
A26: Ibuprofeno Xarope 120ml - Eurofarma | B26: 28980 | C26: 18489
A27: Ibuprofeno 50mg - 30 Comprimidos - Bayer | B27: 237330 | C27: 229870
A28: Vacina contra Artrite - Dose Única | B28: 47166 | C28: 40021
A29: Soro Fisiológico Sempre Livre 400ml | B29: 109170 | C29: 102710
A30: Vacina contra Úlcera - Reforço | B30: 217992 | C30: 211773
A31: Água Micelar Colgate 200ml | B31: 33840 | C31: 28282
A32: Vacina contra Depressão - Dose Única | B32: 461956 | C32: 451064
A33: Paracetamol 500mg - 20 Comprimidos - Bayer | B33: 43434 | C33: 33688
A34: Termômetro Digital CeraVe 50 Metros | B34: 34470 | C34: 28621
A35: Paracetamol Suspensão Oral 50ml - Medley (Genérico) | B35: 358830 | C35: 351133
A36: Soro Fisiológico Clear 50 Metros | B36: 48774 | C36: 40173
... A601: Cefalexina 25mg - 30 Comprimidos - EMS (Genérico) | B601: 0 | C601: -3098

Sheet DashBoard
A1: Painel de desempenho Comercial
A5: Modifique os gráficos com as células azul claras
A7: 8
A22: Clientes | R22: Volume

Sheet DistDespesa
A1: Fornecedores | B1: Gasto Total | D1: Nome | E1: Valor
A2: {=_xlfn.UNIQUE(TbDespesas[nomefornecedor])} -> Freitas Cassiano e Filhos | B2: {=SUMIFS(TbDespesas[valor_total_despesa], TbDespesas[nomefornecedor],_xlfn.ANCHORARRAY( A2))} -> 34764 | D2: {=_xlfn.TAKE(_xlfn._xlws.SORT(_xlfn.HSTACK(_xlfn.ANCHORARRAY(A2),_xlfn.ANCHORARRAY( B2)), 2, -1), DashBoard!A7)} -> Fonseca S/A | E2: 91483
A3: Monteiro - ME | B3: 47614 | D3: Costela Silveira - EI | E3: 91199
A4: Vieira das Neves Ltda. | B4: 2576 | D4: Nascimento | E4: 78597
A5: da Luz | B5: 25681 | D5: Duarte | E5: 75160
A6: Monteiro Ltda. | B6: 40768 | D6: Moreira | E6: 74887
A7: Andrade | B7: 13274 | D7: Rezende | E7: 73436
A8: Castro | B8: 41570 | D8: Fernandes | E8: 73393
A9: Sousa | B9: 29720 | D9: Freitas - EI | E9: 70524
A10: Nascimento S.A. | B10: 20619
A11: Aragão e Filhos | B11: 29340
A12: Nascimento | B12: 78597
A13: Casa Grande - ME | B13: 49944
A14: Moreira | B14: 74887
A15: Vieira | B15: 41758
A16: Macedo Leão S/A | B16: 33597
A17: Nogueira S/A | B17: 36733
A18: Barros | B18: 24848
A19: Mendonça - EI | B19: 29641
A20: Barbosa Martins S.A. | B20: 27919
A21: da Paz - EI | B21: 12956
... A118: Sales - ME | B118: 1243

Sheet Planilha5
A1: Nomes | B1: Valores | D1: Nome | E1: Valor | N1: TITULO
A2: {=IF(DashBoard!$A$22="Clientes", _xlfn.UNIQUE(TbReceitas[nomecliente]), _xlfn.UNIQUE(TbDespesas[nomefornecedor]))} -> Isaque Albuquerque | B2: {=IF(DashBoard!$A$22="Clientes", SUMIFS(TbReceitas[valor_total_receita], TbReceitas[nomecliente],_xlfn.ANCHORARRAY( A2)), SUMIFS(TbDespesas[valor_total_despesa], TbDespesas[nomefornecedor],_xlfn.ANCHORARRAY( A2)))} -> 26068 | D2: {=_xlfn.TAKE(_xlfn._xlws.SORT(_xlfn.HSTACK(_xlfn.ANCHORARRAY(A2),_xlfn.ANCHORARRAY( B2)), 2, -1), DashBoard!$A$7)} -> Luiza Aparecida | E2: 406498 | N2: ="Top " & DashBoard!A7 & " " & DashBoard!A22 -> Top 8 Clientes
A3: Enrico Freitas | B3: 33191 | D3: Ana Vitória Fogaça | E3: 398160
A4: Dra. Alana Moreira | B4: 132459 | D4: Lara Rodrigues | E4: 379230
A5: Thiago Rezende | B5: 55637 | D5: Brayan da Mata | E5: 370492
A6: Brenda da Paz | B6: 232044 | D6: Sra. Agatha Pacheco | E6: 357212
A7: Sr. Otávio Nunes | B7: 20691 | D7: Ísis Ramos | E7: 324098
A8: Luiz Felipe Farias | B8: 27006 | D8: Erick Siqueira | E8: 323239
A9: Dr. João Lucas Cavalcante | B9: 183928 | D9: Maria Liz Novais | E9: 320709
A10: Yasmin Pinto | B10: 117704
A11: Ana Vitória Abreu | B11: 120200
A12: Sr. Henry Gomes | B12: 142416
A13: Yan Correia | B13: 153837
A14: Dr. Lucca Duarte | B14: 116665
A15: Vinicius da Cruz | B15: 59184
A16: Heitor Oliveira | B16: 128506
A17: Sr. Juan Cunha | B17: 162754
A18: Miguel Nogueira | B18: 173606
A19: Allana Araújo | B19: 123410
A20: Dr. Mathias Guerra | B20: 216689
A21: Léo Gonçalves | B21: 123537
... A1103: Erick Costa | B1103: 88500
