Workbook
Name EixoX_Tempo: _xlfn.ANCHORARRAY(Apoio_FiltroExtra!$C$2)
Name EixoY_Dinheiro: _xlfn.ANCHORARRAY(Apoio_FiltroExtra!$D$2)

Sheet receita_detalhada
A1: valor_total_receita | B1: quantidade | C1: id_pedido | D1: hora | E1: nomecliente | F1: Logradouro | G1: Bairro | H1: Município | I1: Estado | J1: nomeproduto | K1: categproduto | L1: precvenda | M1: data_transacao | N1: dia_da_semana | O1: dia | P1: mes | Q1: trismeste | R1: ano
A2: 454.94 | B2: 2 | C2: 1 | D2: 0.13151797 | E2: João Gabriel Gonçalves | F2: Esplanada de da Rocha | G2: Vila Copasa | H2: Sales | I2: PE | J2: Absorvente com Abas Rexona FPS 70 | K2: Fitoterápicos | L2: 227.47 | M2: 46208 | N2: Sunday | O2: 5 | P2: 7 | Q2: 3 | R2: 2026
A3: 676.92 | B3: 4 | C3: 2 | D3: 0.31568582 | E3: Sr. Rafael Gonçalves | F3: Passarela Noah Nogueira | G3: Vila Jardim Leblon | H3: da Rocha | I3: PI | J3: Metformina 500mg - 20 Comprimidos - Medley (Genérico) | K3: Fraldas e Infantis | L3: 169.23 | M3: 46053 | N3: Saturday | O3: 31 | P3: 1 | Q3: 1 | R3: 2026
A4: 1214.05 | B4: 5 | C4: 3 | D4: 0.79700265 | E4: Elisa Vargas | F4: Lagoa Jade da Paz | G4: Suzana | H4: da Costa de Melo | I4: AL | J4: Paracetamol 1g - 10 Comprimidos - Bayer | K4: Vacinas | L4: 242.81 | M4: 45866 | N4: Monday | O4: 28 | P4: 7 | Q4: 3 | R4: 2025
A5: 705.52 | B5: 4 | C5: 4 | D5: 0.77542214 | E5: Isabel Cardoso | F5: Condomínio Siqueira | G5: Conjunto Bonsucesso | H5: Pastor | I5: MG | J5: Shampoo Anticaspa Clear 90g | K5: Antitérmicos | L5: 176.38 | M5: 45951 | N5: Tuesday | O5: 21 | P5: 10 | Q5: 4 | R5: 2025
A6: 38.04 | B6: 4 | C6: 5 | D6: 0.9058455 | E6: Diogo Casa Grande | F6: Condomínio Aurora Cardoso | G6: Vila Copasa | H6: Brito Alegre | I6: MS | J6: Dipirona Sódica Gotas 20ml - EMS (Genérico) | K6: Aparelhos Médicos | L6: 9.51 | M6: 46259 | N6: Tuesday | O6: 25 | P6: 8 | Q6: 3 | R6: 2026
A7: 617.49 | B7: 3 | C7: 6 | D7: 0.21638725 | E7: Ravy Rios | F7: Núcleo de da Cunha | G7: Alta Tensão 1ª Seção | H7: Brito | I7: MS | J7: Curativos (Band-Aid) Mió 200ml | K7: Produtos Ortopédicos | L7: 205.83 | M7: 45865 | N7: Sunday | O7: 27 | P7: 7 | Q7: 3 | R7: 2025
A8: 117.35 | B8: 5 | C8: 7 | D8: 0.24946616 | E8: Caleb da Cunha | F8: Parque Camila Pires | G8: Ouro Minas | H8: Porto | I8: GO | J8: Omeprazol Pomada 30g - Neo Química (Genérico) | K8: Primeiros Socorros | L8: 23.47 | M8: 45744 | N8: Friday | O8: 28 | P8: 3 | Q8: 1 | R8: 2025
A9: 17.85 | B9: 1 | C9: 8 | D9: 0.36061683 | E9: Lara Teixeira | F9: Favela de Pires | G9: Vila Pinho | H9: Nunes do Sul | I9: MA | J9: Pomada para Assaduras Dove FPS 70 | K9: Fraldas e Infantis | L9: 17.85 | M9: 45977 | N9: Sunday | O9: 16 | P9: 11 | Q9: 4 | R9: 2025
A10: 695.52 | B10: 3 | C10: 9 | D10: 0.62453093 | E10: Levi Almeida | F10: Largo Castro | G10: Flamengo | H10: Cardoso | I10: AL | J10: Vacina contra Linfoma - Reforço | K10: Nutrição Infantil | L10: 231.84 | M10: 45773 | N10: Saturday | O10: 26 | P10: 4 | Q10: 2 | R10: 2025
A11: 335.58 | B11: 3 | C11: 10 | D11: 0.55041662 | E11: Ana Pereira | F11: Ladeira Cauã Aragão | G11: Boa União 2ª Seção | H11: da Conceição | I11: DF | J11: Sabonete em Barra Dove FPS 70 | K11: Antibióticos | L11: 111.86 | M11: 46251 | N11: Monday | O11: 17 | P11: 8 | Q11: 3 | R11: 2026
A12: 12.7 | B12: 5 | C12: 11 | D12: 0.72196495 | E12: Gustavo Henrique Campos | F12: Avenida Cecilia Garcia | G12: Alto Caiçaras | H12: Lopes dos Dourados | I12: PB | J12: Curativos (Band-Aid) Vichy FPS 70 | K12: Fraldas e Infantis | L12: 2.54 | M12: 45768 | N12: Monday | O12: 21 | P12: 4 | Q12: 2 | R12: 2025
A13: 233.21 | B13: 1 | C13: 12 | D13: 0.468649 | E13: Maria Julia Vargas | F13: Avenida José Rezende | G13: Vila Maloca | H13: Sales | I13: PE | J13: Vacina contra Epilepsia - Dose Única | K13: Fitoterápicos | L13: 233.21 | M13: 45782 | N13: Monday | O13: 5 | P13: 5 | Q13: 2 | R13: 2025
... A3001: 90.25 | B3001: 5 | C3001: 3000 | D3001: 0.99509543 | E3001: Emilly Costela | F3001: Passarela Monteiro | G3001: Conjunto Califórnia I | H3001: Siqueira do Norte | I3001: RO | J3001: Enalapril 50mg - 30 Comprimidos - Eurofarma | K3001: Analgésicos | L3001: 18.05 | M3001: 45554 | N3001: Thursday | O3001: 19 | P3001: 9 | Q3001: 3 | R3001: 2024

Sheet receita_agregada
A1: valor_total_receita | B1: quantidade_vendida_dia | C1: nomecliente | D1: Logradouro | E1: Bairro | F1: Município | G1: Estado | H1: nomeproduto | I1: categproduto | J1: precvenda | K1: data_transacao | L1: dia_da_semana | M1: dia | N1: mes | O1: trimestre | P1: ano
A2: 540.25 | B2: 5 | C2: Sr. Dante da Mota | D2: Núcleo João Miguel Casa Grande | E2: Palmares | F2: Casa Grande do Oeste | G2: MT | H2: Condicionador Hidratação G-Tech FPS 50 | I2: Produtos Ortopédicos | J2: 108.05 | K2: 46032 | L2: Saturday | M2: 10 | N2: 1 | O2: 1 | P2: 2026
A3: 125.4 | B3: 4 | C3: Dr. Heitor Vieira | D3: Parque Camargo | E3: Eymard | F3: Nogueira de Rios | G3: PR | H3: Azitromicina Xarope 120ml - Medley (Genérico) | I3: Antibióticos | J3: 31.35 | K3: 45927 | L3: Saturday | M3: 27 | N3: 9 | O3: 3 | P3: 2025
A4: 866.95 | B4: 5 | C4: Cecília Pires | D4: Fazenda Theodoro da Luz | E4: Vila São Rafael | F4: Rezende | G4: DF | H4: Atenolol Xarope 120ml - Medley (Genérico) | I4: Fitoterápicos | J4: 173.39 | K4: 46135 | L4: Thursday | M4: 23 | N4: 4 | O4: 2 | P4: 2026
A5: 386.84 | B5: 2 | C5: Sr. Thomas Vasconcelos | D5: Viela Pedro Miguel da Paz | E5: Maria Tereza | F5: Cardoso | G5: AL | H5: Enalapril Suspensão Oral 50ml - Eurofarma | I5: Saúde Bucal | J5: 193.42 | K5: 46199 | L5: Friday | M5: 26 | N5: 6 | O5: 2 | P5: 2026
A6: 911.3 | B6: 5 | C6: Ana Luiza Moura | D6: Lago de da Mota | E6: Alta Tensão 1ª Seção | F6: Machado | G6: PE | H6: Vacina contra Trombose - Reforço | I6: Fitoterápicos | J6: 182.26 | K6: 45856 | L6: Friday | M6: 18 | N6: 7 | O6: 3 | P6: 2025
A7: 310.98 | B7: 3 | C7: Nicolas Moura | D7: Sítio da Luz | E7: Planalto | F7: da Luz de Ramos | G7: SC | H7: Losartana Potássica Xarope 120ml - EMS (Genérico) | I7: Dermocosméticos | J7: 103.66 | K7: 45619 | L7: Saturday | M7: 23 | N7: 11 | O7: 4 | P7: 2024
A8: 79.68 | B8: 1 | C8: Sara Martins | D8: Loteamento Jade Casa Grande | E8: Vista Do Sol | F8: Macedo de Costa | G8: RJ | H8: Sabonete Líquido Panvel 90g | I8: Nutrição Infantil | J8: 79.68 | K8: 46143 | L8: Friday | M8: 1 | N8: 5 | O8: 2 | P8: 2026
A9: 316.11 | B9: 3 | C9: Sara Costa | D9: Largo Cauê Sousa | E9: Cônego Pinheiro 1ª Seção | F9: Gonçalves | G9: MT | H9: Hidroclorotiazida 50mg - 30 Comprimidos - EMS (Genérico) | I9: Analgésicos | J9: 105.37 | K9: 45606 | L9: Sunday | M9: 10 | N9: 11 | O9: 4 | P9: 2024
A10: 70.41 | B10: 3 | C10: Cecilia da Conceição | D10: Praia de Teixeira | E10: Flamengo | F10: Viana | G10: TO | H10: Omeprazol Pomada 30g - Neo Química (Genérico) | I10: Primeiros Socorros | J10: 23.47 | K10: 46268 | L10: Thursday | M10: 3 | N10: 9 | O10: 3 | P10: 2026
A11: 620.2 | B11: 5 | C11: Yago da Luz | D11: Feira Guerra | E11: Miramar | F11: Siqueira do Norte | G11: RO | H11: Cefalexina 25mg - 30 Comprimidos - Neo Química (Genérico) | I11: Antitérmicos | J11: 124.04 | K11: 46168 | L11: Tuesday | M11: 26 | N11: 5 | O11: 2 | P11: 2026
A12: 852.85 | B12: 5 | C12: Luiz Felipe Pastor | D12: Rodovia Macedo | E12: Jardim Do Vale | F12: Castro | G12: RR | H12: Amoxicilina Suspensão Oral 50ml - Eurofarma | I12: Vacinas | J12: 170.57 | K12: 45924 | L12: Wednesday | M12: 24 | N12: 9 | O12: 3 | P12: 2025
A13: 173.32 | B13: 1 | C13: João Guilherme Jesus | D13: Rodovia Sampaio | E13: São Tomaz | F13: da Costa | G13: PE | H13: Vacina contra Diabetes Tipo 1 - Dose Única | I13: Antidepressivos | J13: 173.32 | K13: 45676 | L13: Sunday | M13: 19 | N13: 1 | O13: 1 | P13: 2025
... A3001: 1122.95 | B3001: 5 | C3001: Gael Henrique da Mata | D3001: Praça Ramos | E3001: Planalto | F3001: Montenegro Alegre | G3001: BA | H3001: Vacina contra Desnutrição - Dose Única | I3001: Homeopatia | J3001: 224.59 | K3001: 46104 | L3001: Monday | M3001: 23 | N3001: 3 | O3001: 1 | P3001: 2026

Sheet despesa
A1: iddespesa | B1: data_transacao | C1: dia_da_semana | D1: dia | E1: mes | F1: trismeste | G1: ano | H1: nomefornecedor | I1: nomeproduto | J1: categproduto | K1: quantidade | L1: preco_unitario | M1: valor_total_despesa
A2: 1 | B2: 46067 | C2: Saturday | D2: 14 | E2: 2 | F2: 1 | G2: 2026 | H2: Viana | I2: Atenolol Gotas 20ml - Neo Química (Genérico) | J2: Nutrição Infantil | K2: 48 | L2: 7 | M2: 372
A3: 2 | B3: 46067 | C3: Saturday | D3: 14 | E3: 2 | F3: 1 | G3: 2026 | H3: Viana | I3: Sildenafila 50mg - 30 Comprimidos - Aché | J3: Antidepressivos | K3: 48 | L3: 1 | M3: 66
A4: 3 | B4: 46067 | C4: Saturday | D4: 14 | E4: 2 | F4: 1 | G4: 2026 | H4: Viana | I4: Losartana Potássica 500mg - 20 Comprimidos - Eurofarma | J4: Primeiros Socorros | K4: 44 | L4: 3 | M4: 144
A5: 4 | B5: 46067 | C5: Saturday | D5: 14 | E5: 2 | F5: 1 | G5: 2026 | H5: Viana | I5: Shampoo Anticaspa Colgate Tamanho G (32 un) | J5: Produtos Ortopédicos | K5: 47 | L5: 3 | M5: 158
A6: 5 | B6: 46067 | C6: Saturday | D6: 14 | E6: 2 | F6: 1 | G6: 2026 | H6: Viana | I6: Vacina contra Dermatite - Dose Única | J6: Genéricos | K6: 48 | L6: 8 | M6: 430
A7: 6 | B7: 46067 | C7: Saturday | D7: 14 | E7: 2 | F7: 1 | G7: 2026 | H7: Viana | I7: Metformina 25mg - 30 Comprimidos - Medley (Genérico) | J7: Higiene Pessoal | K7: 29 | L7: 10 | M7: 301
A8: 7 | B8: 45606 | C8: Sunday | D8: 10 | E8: 11 | F8: 4 | G8: 2024 | H8: Machado | I8: Enalapril 50mg - 30 Comprimidos - Eurofarma | J8: Analgésicos | K8: 32 | L8: 9 | M8: 298
A9: 8 | B9: 45606 | C9: Sunday | D9: 10 | E9: 11 | F9: 4 | G9: 2024 | H9: Machado | I9: Amoxicilina 1g - 10 Comprimidos - EMS (Genérico) | J9: Antidepressivos | K9: 40 | L9: 6 | M9: 275
A10: 9 | B10: 45606 | C10: Sunday | D10: 10 | E10: 11 | F10: 4 | G10: 2024 | H10: Machado | I10: Metformina Suspensão Oral 50ml - Medley (Genérico) | J10: Antidepressivos | K10: 28 | L10: 9 | M10: 276
A11: 10 | B11: 46218 | C11: Wednesday | D11: 15 | E11: 7 | F11: 3 | G11: 2026 | H11: Barbosa - EI | I11: Losartana Potássica Gotas 20ml - Medley (Genérico) | J11: Antitérmicos | K11: 12 | L11: 23 | M11: 276
A12: 11 | B12: 46218 | C12: Wednesday | D12: 15 | E12: 7 | F12: 3 | G12: 2026 | H12: Barbosa - EI | I12: Metformina 1g - 10 Comprimidos - Aché | J12: Fraldas e Infantis | K12: 33 | L12: 15 | M12: 495
A13: 12 | B13: 46218 | C13: Wednesday | D13: 15 | E13: 7 | F13: 3 | G13: 2026 | H13: Barbosa - EI | I13: Metformina 1g - 10 Comprimidos - Medley (Genérico) | J13: Antitérmicos | K13: 26 | L13: 8 | M13: 210
... A1926: 1925 | B1926: 45990 | C1926: Saturday | D1926: 29 | E1926: 11 | F1926: 4 | G1926: 2025 | H1926: Macedo | I1926: Protetor Solar Corporal Rexona 150ml | J1926: Antibióticos | K1926: 16 | L1926: 16 | M1926: 265

Sheet Dashboard
A1: Dashboard Comercial e Financeiro - CFB Farmácia
A4: 4 | H4: Estado | I4: 8 | O4: mes
A18: Faturamento | B18: 3 | O18: Cidade | P18: Aragão da Serra | Q18: Ano

Sheet Apoio_FiltroExtra
A2: {=_xlfn.UNIQUE(INDIRECT("receita_detalhada[" & VLOOKUP(Dashboard!$O$18, Q:R, 2, 0) & "]"))} -> Sales | C2: {=_xlfn._xlws.SORT(_xlfn.UNIQUE(INDIRECT("receita_detalhada[" & VLOOKUP(Dashboard!$Q$18, Q:R, 2, 0) & "]")), 1, 1)} -> 2024 | D2: {=SUMIFS(receita_detalhada[valor_total_receita], INDIRECT("receita_detalhada[" & VLOOKUP(Dashboard!$Q$18, Q:R, 2, 0) & "]"),_xlfn.ANCHORARRAY( C2), INDIRECT("receita_detalhada[" & VLOOKUP(Dashboard!$O$18, Q:R, 2, 0) & "]"), Dashboard!$P$18)} -> 627.19
A3: da Rocha | C3: 2025 | D3: 1102.51 | Q3: Logradouro | R3: Logradouro
A4: da Costa de Melo | C4: 2026 | D4: 785.86 | Q4: Bairro | R4: Bairro
A5: Pastor | Q5: Cidade | R5: Município
A6: Brito Alegre | Q6: Estado | R6: Estado
A7: Brito | Q7: Ano | R7: ano
A8: Porto | Q8: Mês | R8: mes
A9: Nunes do Sul | M9: ="Faturamento em " & Dashboard!P18 & " por " & Dashboard!Q18 -> Faturamento em Aragão da Serra por Ano | Q9: Dia Semana | R9: dia_da_semana
A10: Cardoso | Q10: Data Completa | R10: data_transacao
A11: da Conceição
A12: Lopes dos Dourados
A13: Albuquerque das Flores
A14: Pimenta da Praia
A15: Nunes
A16: Vargas
A17: Macedo Alegre
A18: da Costa
A19: Pires
A20: Leão
A21: Nogueira
A22: Vieira de Minas
... A166: Sousa da Praia

Sheet Apoio_Financeiro
A1: Mês | B1: Receita | C1: Despesa | D1: Lucro
A2: {=_xlfn._xlws.SORT(_xlfn.UNIQUE(receita_agregada[mes]), 1, 1)} -> 1 | B2: {=SUMIFS(receita_agregada[valor_total_receita], receita_agregada[mes],_xlfn.ANCHORARRAY( A2))} -> 102398.64 | C2: {=SUMIFS(despesa[valor_total_despesa], despesa[mes],_xlfn.ANCHORARRAY( A2))} -> 42996 | D2: {=_xlfn.ANCHORARRAY(B2) -_xlfn.ANCHORARRAY( C2)} -> 59402.64
A3: 2 | B3: 81737.12 | C3: 37166 | D3: 44571.12
A4: 3 | B4: 100090.12 | C4: 20686 | D4: 79404.12
A5: 4 | B5: 82097.47 | C5: 42058 | D5: 40039.47
A6: 5 | B6: 87155.04 | C6: 29593 | D6: 57562.04
A7: 6 | B7: 78053.12 | C7: 42751 | D7: 35302.12
A8: 7 | B8: 88304.66 | C8: 48572 | D8: 39732.66
A9: 8 | B9: 77131.75 | C9: 37343 | D9: 39788.75
A10: 9 | B10: 89651.93 | C10: 48742 | D10: 40909.93
A11: 10 | B11: 94132.42 | C11: 67849 | D11: 26283.42
A12: 11 | B12: 83021.04 | C12: 41941 | D12: 41080.04
A13: 12 | B13: 90869.07 | C13: 22714 | D13: 68155.07

Sheet Apoio_Tempo
A2: {=_xlfn.UNIQUE(INDIRECT("receita_agregada["&Dashboard!$O$4&"]"))} -> 1 | B2: {=SUMIFS(receita_agregada[valor_total_receita],INDIRECT("receita_agregada["&Dashboard!$O$4&"]"),_xlfn.ANCHORARRAY(A2))} -> 102398.64 | D2: {=_xlfn._xlws.SORT(_xlfn.HSTACK(_xlfn.ANCHORARRAY(A2),_xlfn.ANCHORARRAY( B2)), 1, 1)} -> 1 | E2: 102398.64
A3: 9 | B3: 89651.93 | D3: 2 | E3: 81737.12
A4: 4 | B4: 82097.47 | D4: 3 | E4: 100090.12
A5: 6 | B5: 78053.12 | D5: 4 | E5: 82097.47
A6: 7 | B6: 88304.66 | D6: 5 | E6: 87155.04
A7: 11 | B7: 83021.04 | D7: 6 | E7: 78053.12
A8: 5 | B8: 87155.04 | D8: 7 | E8: 88304.66 | O8: ="Evolução de Receitas por " & Dashboard!O4 -> Evolução de Receitas por mes
A9: 12 | B9: 90869.07 | D9: 8 | E9: 77131.75
A10: 2 | B10: 81737.12 | D10: 9 | E10: 89651.93
A11: 10 | B11: 94132.42 | D11: 10 | E11: 94132.42
A12: 8 | B12: 77131.75 | D12: 11 | E12: 83021.04
A13: 3 | B13: 100090.12 | D13: 12 | E13: 90869.07

Sheet Apoio_Cliente
A2: {=_xlfn.UNIQUE(receita_detalhada[nomecliente])} -> João Gabriel Gonçalves | B2: {=SUMIFS(receita_detalhada[valor_total_receita], receita_detalhada[nomecliente],_xlfn.ANCHORARRAY( A2))} -> 918.08 | C2: {=_xlfn.TAKE(_xlfn._xlws.SORT(_xlfn.HSTACK(_xlfn.ANCHORARRAY(A2),_xlfn.ANCHORARRAY( B2)), 2, -1), Dashboard!$A$4)} -> Pedro Henrique Aragão | D2: 4096.26
A3: Sr. Rafael Gonçalves | B3: 748.43 | C3: Luiz Felipe Casa Grande | D3: 4000.22 | M3: ="Top " & Dashboard!A4 & " clientes por faturamento" -> Top 4 clientes por faturamento
A4: Elisa Vargas | B4: 1615.44 | C4: Emilly Araújo | D4: 3959.83
A5: Isabel Cardoso | B5: 924.78 | C5: Benjamin Nascimento | D5: 3772.97
A6: Diogo Casa Grande | B6: 173.51
A7: Ravy Rios | B7: 1833.64
A8: Caleb da Cunha | B8: 345.86
A9: Lara Teixeira | B9: 220.45
A10: Levi Almeida | B10: 1141.67
A11: Ana Pereira | B11: 836.37
A12: Gustavo Henrique Campos | B12: 1108.31
A13: Maria Julia Vargas | B13: 2607.09
A14: Sofia Andrade | B14: 644.78
A15: João Pedro Caldeira | B15: 1543.81
A16: Esther Machado | B16: 1247.82
A17: Fernando Pereira | B17: 2503.14
... A1095: Nicolas Castro | B1095: 180.26

Sheet Apoio_Produto
A2: {=_xlfn.UNIQUE(receita_detalhada[nomeproduto])} -> Absorvente com Abas Rexona FPS 70 | B2: {=IF(Dashboard!$A$18="Faturamento", SUMIFS(receita_detalhada[valor_total_receita], receita_detalhada[nomeproduto],_xlfn.ANCHORARRAY( A2)), SUMIFS(receita_detalhada[quantidade], receita_detalhada[nomeproduto],_xlfn.ANCHORARRAY( A2)))} -> 5914.22 | D2: {=_xlfn.TAKE(_xlfn._xlws.SORT(_xlfn.HSTACK(_xlfn.ANCHORARRAY(A2),_xlfn.ANCHORARRAY( B2)), 2, -1), Dashboard!$B$18)} -> Pantoprazol Pomada 30g - Medley (Genérico) | E2: 7952.94
A3: Metformina 500mg - 20 Comprimidos - Medley (Genérico) | B3: 1353.84 | D3: Vacina contra Desnutrição - Dose Única | E3: 7636.06
A4: Paracetamol 1g - 10 Comprimidos - Bayer | B4: 3642.15 | D4: Escitalopram Suspensão Oral 50ml - Eurofarma | E4: 7017.42
A5: Shampoo Anticaspa Clear 90g | B5: 2998.46
A6: Dipirona Sódica Gotas 20ml - EMS (Genérico) | B6: 161.67 | K6: ="Top " & Dashboard!B18 & " Produtos por " & Dashboard!A18 -> Top 3 Produtos por Faturamento
A7: Curativos (Band-Aid) Mió 200ml | B7: 2058.3
A8: Omeprazol Pomada 30g - Neo Química (Genérico) | B8: 516.34
A9: Pomada para Assaduras Dove FPS 70 | B9: 232.05
A10: Vacina contra Linfoma - Reforço | B10: 5564.16
A11: Sabonete em Barra Dove FPS 70 | B11: 2908.36
A12: Curativos (Band-Aid) Vichy FPS 70 | B12: 43.18
A13: Vacina contra Epilepsia - Dose Única | B13: 3964.57
A14: Condicionador Hidratação G-Tech Tamanho G (32 un) | B14: 951.21
A15: Desodorante Aerosol Nivea 200ml | B15: 2204.16
A16: Vacina contra Parkinson - Reforço | B16: 200.34
A17: Vacina contra Dengue - Reforço | B17: 1125.18
A18: Ibuprofeno Suspensão Oral 50ml - Eurofarma | B18: 3636.75
... A599: Fralda Descartável Vichy 400ml | B599: 274.6

Sheet Apoio_Regiao
A2: {=IF(Dashboard!$H$4="Bairro", _xlfn.UNIQUE(receita_detalhada[Bairro]), IF(Dashboard!$H$4="Município", _xlfn.UNIQUE(receita_detalhada[Município]), _xlfn.UNIQUE(receita_detalhada[Estado])))} -> PE | B2: {=SUMIFS(receita_detalhada[valor_total_receita], INDIRECT("receita_detalhada["&Dashboard!$H$4&"]"),_xlfn.ANCHORARRAY( A2))} -> 58625.7 | D2: {=_xlfn.TAKE(_xlfn._xlws.SORT(_xlfn.HSTACK(_xlfn.ANCHORARRAY(A2),_xlfn.ANCHORARRAY( B2)), 2, -1), Dashboard!$I$4)} -> PE | E2: 58625.7
A3: PI | B3: 19010.23 | D3: BA | E3: 58263.85
A4: AL | B4: 42501.15 | D4: PB | E4: 57122.16
A5: MG | B5: 19128.75 | D5: RR | E5: 56405.57
A6: MS | B6: 29323.86 | D6: DF | E6: 55910.72
A7: GO | B7: 38062.91 | D7: RJ | E7: 54485.54
A8: MA | B8: 41450.36 | D8: PR | E8: 48275.21 | K8: ="Faturamento dos top " & Dashboard!I4 & " " & Dashboard!H4 & " (R$)" -> Faturamento dos top 8 Estado (R$)
A9: DF | B9: 55910.72 | D9: RO | E9: 47957.19
A10: PB | B10: 57122.16
A11: RN | B11: 32197.08
A12: SE | B12: 27631.84
A13: RR | B13: 56405.57
A14: PR | B14: 48275.21
A15: RJ | B15: 54485.54
A16: PA | B16: 35197.66
A17: AM | B17: 30483.02
A18: RS | B18: 32852.15
A19: MT | B19: 38523.95
A20: AC | B20: 34499.08
A21: TO | B21: 32779.02
... A28: SC | B28: 27773.94
